wyylde_sdk/__init__.py
wyylde_sdk/client.py
wyylde_sdk/models/__init__.py
wyylde_sdk/models/contact.py
wyylde_sdk/models/crush.py
wyylde_sdk/models/event.py
wyylde_sdk/models/talk.py
wyylde_sdk/models/testimony.py
wyylde_sdk/models/user.py
wyylde_sdk/models/visit.py
wyylde_sdk/py.typed
wyylde_sdk-1.3.8.dist-info/entry_points.txt
wyylde_sdk-1.3.8.dist-info/LICENSE
wyylde_sdk-1.3.8.dist-info/WHEEL
wyylde_sdk-1.3.8.dist-info/METADATA
wyylde_sdk-1.3.8.dist-info/RECORD
