Metadata-Version: 2.1
Name: wyylde-sdk
Version: 1.3.8
Summary: Wyylde SDK
Home-page: https://github.com/Dogeek/wyylde-sdk
License: MIT
Author: Dogeek
Author-email: simon.bordeyne@gmail.com
Requires-Python: >=3.7,<4.0
Classifier: Development Status :: 5 - Production/Stable
Classifier: License :: OSI Approved :: MIT License
Classifier: Programming Language :: Python :: 3
Classifier: Programming Language :: Python :: 3.10
Classifier: Programming Language :: Python :: 3.7
Classifier: Programming Language :: Python :: 3.8
Classifier: Programming Language :: Python :: 3.9
Requires-Dist: dacite (>=1.6.0,<2.0.0)
Requires-Dist: requests (>=2.28.1,<3.0.0)
Project-URL: Changelog, https://github.com/Dogeek/wyylde-sdk/releases
Project-URL: Documentation, https://wyylde-sdk.readthedocs.io
Project-URL: Repository, https://github.com/Dogeek/wyylde-sdk
